matrixsketcher/Fast_Walsh-Hadamard_Transform.py
matrixsketcher/__init__.py
matrixsketcher/_utils.py
matrixsketcher/bicriteria_cur.py
matrixsketcher/countsketch.py
matrixsketcher/cur_decomposition.py
matrixsketcher/leverage_score.py
matrixsketcher-0.1.3.dist-info/LICENSE
matrixsketcher-0.1.3.dist-info/METADATA
matrixsketcher-0.1.3.dist-info/WHEEL
matrixsketcher-0.1.3.dist-info/top_level.txt
matrixsketcher-0.1.3.dist-info/RECORD
