Metadata-Version: 2.2
Name: matrixsketcher
Version: 0.1.3
Summary: A collection of efficient matrix sketching methods
Home-page: https://github.com/luke-brosnan-cbc/MatrixSketcher
Author: Luke Brosnan
Author-email: luke.brosnan.cbc@gmail.com
Classifier: Programming Language :: Python :: 3.10
Classifier: Programming Language :: Python :: 3.11
Classifier: Programming Language :: Python :: 3.12
Classifier: Programming Language :: Python :: 3.13
Requires-Python: >=3.10
License-File: LICENSE
Requires-Dist: numpy
Requires-Dist: scipy
Dynamic: author
Dynamic: author-email
Dynamic: classifier
Dynamic: home-page
Dynamic: requires-dist
Dynamic: requires-python
Dynamic: summary
